langchain_azure_dynamic_sessions/__init__.py
langchain_azure_dynamic_sessions/py.typed
langchain_azure_dynamic_sessions/tools/__init__.py
langchain_azure_dynamic_sessions/tools/sessions.py
langchain_azure_dynamic_sessions-0.3.1.dist-info/LICENSE
langchain_azure_dynamic_sessions-0.3.1.dist-info/METADATA
langchain_azure_dynamic_sessions-0.3.1.dist-info/WHEEL
langchain_azure_dynamic_sessions-0.3.1.dist-info/RECORD
