Metadata-Version: 2.3
Name: langchain-azure-dynamic-sessions
Version: 0.3.1
Summary: An integration package connecting Azure Container Apps dynamic sessions and LangChain
License: MIT License
Requires-Python: >=3.10,<4.0
Classifier: License :: Other/Proprietary License
Classifier: Programming Language :: Python :: 3
Classifier: Programming Language :: Python :: 3.10
Classifier: Programming Language :: Python :: 3.11
Classifier: Programming Language :: Python :: 3.12
Classifier: Programming Language :: Python :: 3.13
Requires-Dist: azure-identity (>=1.16,<2.0)
Requires-Dist: langchain-core (>=1.0.1)
Requires-Dist: requests (>=2.31,<3.0)
Project-URL: Repository, https://github.com/langchain-ai/langchain-azure
Project-URL: Release Notes, https://github.com/langchain-ai/langchain-azure/releases
Project-URL: Source Code, https://github.com/langchain-ai/langchain-azure/tree/main/libs/azure-dynamic-sessions
